[
  {
    "rank": 1,
    "layer": 1,
    "head": 17,
    "score": 0.478271484375
  },
  {
    "rank": 2,
    "layer": 7,
    "head": 15,
    "score": 0.1578369140625
  },
  {
    "rank": 3,
    "layer": 1,
    "head": 3,
    "score": 0.117431640625
  },
  {
    "rank": 4,
    "layer": 1,
    "head": 2,
    "score": 0.10552978515625
  },
  {
    "rank": 5,
    "layer": 24,
    "head": 16,
    "score": 0.087890625
  },
  {
    "rank": 6,
    "layer": 14,
    "head": 11,
    "score": 0.0806884765625
  },
  {
    "rank": 7,
    "layer": 34,
    "head": 4,
    "score": 0.07403564453125
  },
  {
    "rank": 8,
    "layer": 30,
    "head": 7,
    "score": 0.072021484375
  },
  {
    "rank": 9,
    "layer": 24,
    "head": 11,
    "score": 0.07171630859375
  },
  {
    "rank": 10,
    "layer": 30,
    "head": 16,
    "score": 0.069091796875
  },
  {
    "rank": 11,
    "layer": 17,
    "head": 6,
    "score": 0.06854248046875
  },
  {
    "rank": 12,
    "layer": 21,
    "head": 10,
    "score": 0.06842041015625
  },
  {
    "rank": 13,
    "layer": 17,
    "head": 2,
    "score": 0.066162109375
  },
  {
    "rank": 14,
    "layer": 30,
    "head": 12,
    "score": 0.063720703125
  },
  {
    "rank": 15,
    "layer": 21,
    "head": 11,
    "score": 0.06298828125
  },
  {
    "rank": 16,
    "layer": 24,
    "head": 3,
    "score": 0.06268310546875
  },
  {
    "rank": 17,
    "layer": 25,
    "head": 13,
    "score": 0.062103271484375
  },
  {
    "rank": 18,
    "layer": 15,
    "head": 7,
    "score": 0.05963134765625
  },
  {
    "rank": 19,
    "layer": 30,
    "head": 11,
    "score": 0.0595703125
  },
  {
    "rank": 20,
    "layer": 21,
    "head": 9,
    "score": 0.059539794921875
  }
]